sdlib/__init__.py
sdlib/function_params.py
sdlib/hijacker.py
sdlib/plugin_system.py
sdlib/sdlib.py
sdlib/sd_webui/__init__.py
sdlib/sd_webui/api_impl.py
sdlib/sd_webui/gradio_helpers.py
sdlib/sd_webui/img2img_tabs.py
sdlib/sd_webui/prompt_parser.py
sdlib-0.0.1.dist-info/METADATA
sdlib-0.0.1.dist-info/WHEEL
sdlib-0.0.1.dist-info/top_level.txt
sdlib-0.0.1.dist-info/RECORD
